{
  "clean_clip_positive_margin": 0.027842342853546143,
  "clean_semantic_success_score": 0.027842342853546143,
  "clip_available": true,
  "clip_semantic_drop": -0.0021704435348510742,
  "clip_warning": null,
  "crop_clip_available": true,
  "crop_clip_warning": null,
  "decision_label": "metric_only_candidate",
  "decision_reasons": [
    "semantic_drop_nonpositive:-0.0022",
    "semantic_drop_nonpositive:-0.0022"
  ],
  "edit_failure_score": 0.0,
  "final_attack_score": 0.05913955222746482,
  "full_image_semantic_drop": -0.0021704435348510742,
  "geometry_excess_penalty": 0.0,
  "geometry_excess_penalty_weight": 0.75,
  "identity_or_face_health_available": false,
  "input_damage_penalty": 0.0,
  "input_damage_penalty_weight": 3.0,
  "input_l2": 0.025855410229068752,
  "input_max_abs": 0.5137255191802979,
  "input_mean_abs": 0.00842142105102539,
  "input_preservation_score": 0.40169538770403185,
  "input_psnr": 31.748971344024653,
  "input_ssim": 0.9162373542785645,
  "left_crop_clean_margin": 0.02535329759120941,
  "left_crop_perturbed_margin": 0.0214044451713562,
  "left_crop_semantic_drop": 0.0039488524198532104,
  "max_disp_px_budget": 8.0,
  "mean_crop_margin": 0.011812850832939148,
  "mean_crop_semantic_drop": 0.006298417846361796,
  "min_crop_margin": -0.004308223724365234,
  "min_crop_semantic_drop": 0.003139197826385498,
  "output_disruption_score": 0.2365582089098593,
  "output_disruption_weight": 0.25,
  "output_l2": 0.03383416186949363,
  "output_max_abs": 0.6431372761726379,
  "output_mean_abs": 0.017040085047483444,
  "output_psnr": 29.4128915454027,
  "output_ssim": 0.8987784385681152,
  "perturbed_clip_positive_margin": 0.030012786388397217,
  "perturbed_semantic_success_score": 0.030012786388397217,
  "phase2_final_score": 0.05913955222746482,
  "phase2_output_disruption": 0.2365582089098593,
  "phase2_score_formula": "8.0*max(0,semantic_drop)+0.25*output_disruption-3.0*input_damage_penalty-0.75*geometry_excess_penalty",
  "right_crop_clean_margin": 0.021481528878211975,
  "right_crop_perturbed_margin": 0.018342331051826477,
  "right_crop_semantic_drop": 0.003139197826385498,
  "semantic_drop": -0.0021704435348510742,
  "semantic_drop_weight": 8.0,
  "target_input_ssim": 0.86,
  "top_crop_clean_margin": 0.007498979568481445,
  "top_crop_perturbed_margin": -0.004308223724365234,
  "top_crop_semantic_drop": 0.01180720329284668
}
