{
  "action_names": [
    "face_side_push_left",
    "face_side_push_right",
    "head_top_raise",
    "head_top_lower",
    "jaw_expand",
    "jaw_compress",
    "asymmetry_twist"
  ],
  "action_strength": 0.72,
  "action_values": {
    "asymmetry_twist": -0.13133510105295187,
    "face_side_push_left": -0.20047156046267006,
    "face_side_push_right": -0.16680741539626381,
    "head_top_lower": 0.189979039744662,
    "head_top_raise": 0.05306682049098109,
    "jaw_compress": 0.22245248853351796,
    "jaw_expand": 0.21603168744169748
  },
  "active_actions": {
    "asymmetry_twist": -0.13133510105295187,
    "face_side_push_left": -0.20047156046267006,
    "face_side_push_right": -0.16680741539626381,
    "head_top_lower": 0.189979039744662,
    "head_top_raise": 0.05306682049098109,
    "jaw_compress": 0.22245248853351796,
    "jaw_expand": 0.21603168744169748
  },
  "active_anchor_count": 7,
  "control_point_count": 15,
  "geometry_method": "landmark_piecewise_affine",
  "landmark_count": 478,
  "landmark_detector": "mediapipe_python_solutions_face_mesh",
  "max_disp_px_budget": 8.0,
  "require_real_landmarks": true,
  "scale_factor": 0.28165371222992286,
  "source_control_points": [
    [
      104.53517150878906,
      219.31192016601562
    ],
    [
      104.53517150878906,
      219.9771728515625
    ],
    [
      363.7645263671875,
      219.31192016601562
    ],
    [
      366.4462585449219,
      219.9771728515625
    ],
    [
      245.24688720703125,
      59.94889831542969
    ],
    [
      121.2041244506836,
      337.6188049316406
    ],
    [
      320.013916015625,
      337.6188049316406
    ],
    [
      0.0,
      0.0
    ],
    [
      511.0,
      0.0
    ],
    [
      0.0,
      511.0
    ],
    [
      511.0,
      511.0
    ],
    [
      256.0,
      0.0
    ],
    [
      256.0,
      511.0
    ],
    [
      0.0,
      256.0
    ],
    [
      511.0,
      256.0
    ]
  ],
  "target_control_points": [
    [
      105.68988800048828,
      220.0684051513672
    ],
    [
      105.40120697021484,
      219.9771728515625
    ],
    [
      362.8037109375,
      218.55543518066406
    ],
    [
      365.72564697265625,
      219.9771728515625
    ],
    [
      245.24688720703125,
      60.73751449584961
    ],
    [
      121.2411117553711,
      337.9970397949219
    ],
    [
      319.9769287109375,
      337.2405700683594
    ],
    [
      0.0,
      0.0
    ],
    [
      511.0,
      0.0
    ],
    [
      0.0,
      511.0
    ],
    [
      511.0,
      511.0
    ],
    [
      256.0,
      0.0
    ],
    [
      256.0,
      511.0
    ],
    [
      0.0,
      256.0
    ],
    [
      511.0,
      256.0
    ]
  ],
  "tps_regularization": 0.0001
}
