{
  "geometry_info": {
    "action_names": [
      "eye_spread",
      "eye_compress",
      "eye_squint",
      "eye_raise_left",
      "eye_raise_right",
      "nose_bridge_shift_x",
      "asymmetry_twist"
    ],
    "action_strength": 0.72,
    "action_values": {
      "asymmetry_twist": 0.4776622194610701,
      "eye_compress": -0.4138989762346385,
      "eye_raise_left": 0.3433966323891779,
      "eye_raise_right": 0.3622864998673676,
      "eye_spread": -0.10219422303161933,
      "eye_squint": -0.08717199493816374,
      "nose_bridge_shift_x": -0.09827701947564779
    },
    "active_actions": {
      "asymmetry_twist": 0.4776622194610701,
      "eye_compress": -0.4138989762346385,
      "eye_raise_left": 0.3433966323891779,
      "eye_raise_right": 0.3622864998673676,
      "eye_spread": -0.10219422303161933,
      "eye_squint": -0.08717199493816374,
      "nose_bridge_shift_x": -0.09827701947564779
    },
    "active_anchor_count": 13,
    "control_point_count": 21,
    "geometry_method": "landmark_semantic_tps",
    "landmark_count": 478,
    "landmark_detector": "mediapipe_python_solutions_face_mesh",
    "max_disp_px_budget": 14.0,
    "require_real_landmarks": true,
    "scale_factor": 0.7143749343589978,
    "source_control_points": [
      [
        196.52999877929688,
        189.3992919921875
      ],
      [
        173.06689453125,
        189.3992919921875
      ],
      [
        299.720458984375,
        172.67965698242188
      ],
      [
        323.55364990234375,
        172.67965698242188
      ],
      [
        196.52999877929688,
        180.7253875732422
      ],
      [
        196.52999877929688,
        198.07318115234375
      ],
      [
        299.720458984375,
        163.08763122558594
      ],
      [
        299.720458984375,
        182.27169799804688
      ],
      [
        241.4825439453125,
        200.3087615966797
      ],
      [
        145.79103088378906,
        230.60910034179688
      ],
      [
        185.86373901367188,
        332.8659362792969
      ],
      [
        383.8033447265625,
        230.60910034179688
      ],
      [
        370.30474853515625,
        332.8659362792969
      ],
      [
        0.0,
        0.0
      ],
      [
        511.0,
        0.0
      ],
      [
        0.0,
        511.0
      ],
      [
        511.0,
        511.0
      ],
      [
        256.0,
        0.0
      ],
      [
        256.0,
        511.0
      ],
      [
        0.0,
        256.0
      ],
      [
        511.0,
        256.0
      ]
    ],
    "target_control_points": [
      [
        193.3880157470703,
        185.93785095214844
      ],
      [
        169.92491149902344,
        189.3992919921875
      ],
      [
        302.8624572753906,
        169.02780151367188
      ],
      [
        326.6956481933594,
        172.67965698242188
      ],
      [
        196.52999877929688,
        176.38525390625
      ],
      [
        196.52999877929688,
        197.22116088867188
      ],
      [
        299.720458984375,
        158.5570831298828
      ],
      [
        299.720458984375,
        181.324462890625
      ],
      [
        240.49191284179688,
        200.3087615966797
      ],
      [
        145.79103088378906,
        225.7942657470703
      ],
      [
        185.86373901367188,
        330.4585266113281
      ],
      [
        383.8033447265625,
        235.42393493652344
      ],
      [
        370.30474853515625,
        335.2733459472656
      ],
      [
        0.0,
        0.0
      ],
      [
        511.0,
        0.0
      ],
      [
        0.0,
        511.0
      ],
      [
        511.0,
        511.0
      ],
      [
        256.0,
        0.0
      ],
      [
        256.0,
        511.0
      ],
      [
        0.0,
        256.0
      ],
      [
        511.0,
        256.0
      ]
    ],
    "tps_regularization": 0.0001
  },
  "names": [
    "scale_logit",
    "action_eye_spread",
    "action_eye_compress",
    "action_eye_squint",
    "action_eye_raise_left",
    "action_eye_raise_right",
    "action_nose_bridge_shift_x",
    "action_asymmetry_twist"
  ],
  "values": [
    0.2941362261772156,
    -0.14404204487800598,
    -0.6615382432937622,
    -0.12263668328523636,
    0.5238880515098572,
    0.558868944644928,
    -0.13844850659370422,
    0.8082858920097351
  ]
}
