{
  "geometry_info": {
    "action_names": [
      "jaw_expand",
      "jaw_compress",
      "chin_raise",
      "chin_lower",
      "mouth_width_expand",
      "lower_face_shift"
    ],
    "action_strength": 0.72,
    "action_values": {
      "chin_lower": 0.24642631176263352,
      "chin_raise": 0.6735860774327389,
      "jaw_compress": -0.059372014186333484,
      "jaw_expand": 0.7482057158949968,
      "lower_face_shift": 0.5752601579220915,
      "mouth_width_expand": 0.26612043176529326
    },
    "active_actions": {
      "chin_lower": 0.24642631176263352,
      "chin_raise": 0.6735860774327389,
      "jaw_compress": -0.059372014186333484,
      "jaw_expand": 0.7482057158949968,
      "lower_face_shift": 0.5752601579220915,
      "mouth_width_expand": 0.26612043176529326
    },
    "active_anchor_count": 6,
    "control_point_count": 14,
    "geometry_method": "landmark_semantic_tps",
    "max_disp_px_budget": 8.0,
    "scale_factor": 0.7912768319381562,
    "source_control_points": [
      [
        174.0800018310547,
        394.239990234375
      ],
      [
        337.9200134277344,
        394.239990234375
      ],
      [
        256.0,
        419.8399963378906
      ],
      [
        256.0,
        376.32000732421875
      ],
      [
        204.8000030517578,
        335.3599853515625
      ],
      [
        307.20001220703125,
        335.3599853515625
      ],
      [
        0.0,
        0.0
      ],
      [
        511.0,
        0.0
      ],
      [
        0.0,
        511.0
      ],
      [
        511.0,
        511.0
      ],
      [
        256.0,
        0.0
      ],
      [
        256.0,
        511.0
      ],
      [
        0.0,
        256.0
      ],
      [
        511.0,
        256.0
      ]
    ],
    "target_control_points": [
      [
        169.42835998535156,
        394.239990234375
      ],
      [
        342.5716552734375,
        394.239990234375
      ],
      [
        258.4851379394531,
        417.3795471191406
      ],
      [
        259.3135070800781,
        375.08978271484375
      ],
      [
        203.26715087890625,
        335.3599853515625
      ],
      [
        308.7328796386719,
        335.3599853515625
      ],
      [
        0.0,
        0.0
      ],
      [
        511.0,
        0.0
      ],
      [
        0.0,
        511.0
      ],
      [
        511.0,
        511.0
      ],
      [
        256.0,
        0.0
      ],
      [
        256.0,
        511.0
      ],
      [
        0.0,
        256.0
      ],
      [
        511.0,
        256.0
      ]
    ],
    "tps_regularization": 0.0001
  },
  "names": [
    "scale_logit",
    "action_jaw_expand",
    "action_jaw_compress",
    "action_chin_raise",
    "action_chin_lower",
    "action_mouth_width_expand",
    "action_lower_face_shift"
  ],
  "values": [
    0.5206377506256104,
    1.7881745100021362,
    -0.07517446577548981,
    1.2607282400131226,
    0.3221267759799957,
    0.34993481636047363,
    0.9223397374153137
  ]
}
