{
  "action_names": [
    "jaw_expand",
    "jaw_compress",
    "chin_raise",
    "chin_lower",
    "mouth_width_expand",
    "lower_face_shift"
  ],
  "action_strength": 0.72,
  "action_values": {
    "chin_lower": 0.6203424629889196,
    "chin_raise": -0.08503779868143055,
    "jaw_compress": -0.4544244264881834,
    "jaw_expand": 0.138902148605012,
    "lower_face_shift": 0.40970818418581384,
    "mouth_width_expand": 0.6091827311011055
  },
  "active_actions": {
    "chin_lower": 0.6203424629889196,
    "chin_raise": -0.08503779868143055,
    "jaw_compress": -0.4544244264881834,
    "jaw_expand": 0.138902148605012,
    "lower_face_shift": 0.40970818418581384,
    "mouth_width_expand": 0.6091827311011055
  },
  "active_anchor_count": 6,
  "control_point_count": 14,
  "geometry_method": "landmark_piecewise_affine",
  "max_disp_px_budget": 8.0,
  "scale_factor": 0.6477992759772577,
  "source_control_points": [
    [
      174.0800018310547,
      394.239990234375
    ],
    [
      337.9200134277344,
      394.239990234375
    ],
    [
      256.0,
      419.8399963378906
    ],
    [
      256.0,
      376.32000732421875
    ],
    [
      204.8000030517578,
      335.3599853515625
    ],
    [
      307.20001220703125,
      335.3599853515625
    ],
    [
      0.0,
      0.0
    ],
    [
      511.0,
      0.0
    ],
    [
      0.0,
      511.0
    ],
    [
      511.0,
      511.0
    ],
    [
      256.0,
      0.0
    ],
    [
      256.0,
      511.0
    ],
    [
      0.0,
      256.0
    ],
    [
      511.0,
      256.0
    ]
  ],
  "target_control_points": [
    [
      170.66244506835938,
      394.239990234375
    ],
    [
      341.33758544921875,
      394.239990234375
    ],
    [
      257.7699279785156,
      423.9029846191406
    ],
    [
      258.35992431640625,
      378.35150146484375
    ],
    [
      201.29110717773438,
      335.3599853515625
    ],
    [
      310.7088928222656,
      335.3599853515625
    ],
    [
      0.0,
      0.0
    ],
    [
      511.0,
      0.0
    ],
    [
      0.0,
      511.0
    ],
    [
      511.0,
      511.0
    ],
    [
      256.0,
      0.0
    ],
    [
      256.0,
      511.0
    ],
    [
      0.0,
      256.0
    ],
    [
      511.0,
      256.0
    ]
  ],
  "tps_regularization": 0.0001
}
