{
  "action_names": [
    "eye_spread",
    "eye_compress",
    "eye_squint",
    "eye_raise_left",
    "eye_raise_right",
    "nose_bridge_shift_x",
    "asymmetry_twist"
  ],
  "action_strength": 0.72,
  "action_values": {
    "asymmetry_twist": 0.0,
    "eye_compress": 0.0,
    "eye_raise_left": 0.0,
    "eye_raise_right": 0.0,
    "eye_spread": 0.0,
    "eye_squint": 0.0,
    "nose_bridge_shift_x": 0.0
  },
  "active_actions": {},
  "active_anchor_count": 13,
  "control_point_count": 21,
  "geometry_method": "landmark_semantic_tps",
  "landmark_count": 478,
  "landmark_detector": "mediapipe_python_solutions_face_mesh",
  "max_disp_px_budget": 8.0,
  "require_real_landmarks": true,
  "scale_factor": 0.6000000000000001,
  "source_control_points": [
    [
      190.21414184570312,
      159.2659912109375
    ],
    [
      163.99778747558594,
      159.2659912109375
    ],
    [
      306.25543212890625,
      175.0582275390625
    ],
    [
      331.9805908203125,
      175.0582275390625
    ],
    [
      190.21414184570312,
      149.36541748046875
    ],
    [
      190.21414184570312,
      169.16656494140625
    ],
    [
      306.25543212890625,
      166.18838500976562
    ],
    [
      306.25543212890625,
      183.92808532714844
    ],
    [
      251.65289306640625,
      190.71658325195312
    ],
    [
      104.53517150878906,
      219.31192016601562
    ],
    [
      121.2041244506836,
      337.6188049316406
    ],
    [
      363.7645263671875,
      219.31192016601562
    ],
    [
      320.013916015625,
      337.6188049316406
    ],
    [
      0.0,
      0.0
    ],
    [
      511.0,
      0.0
    ],
    [
      0.0,
      511.0
    ],
    [
      511.0,
      511.0
    ],
    [
      256.0,
      0.0
    ],
    [
      256.0,
      511.0
    ],
    [
      0.0,
      256.0
    ],
    [
      511.0,
      256.0
    ]
  ],
  "target_control_points": [
    [
      190.21414184570312,
      159.2659912109375
    ],
    [
      163.99778747558594,
      159.2659912109375
    ],
    [
      306.25543212890625,
      175.0582275390625
    ],
    [
      331.9805908203125,
      175.0582275390625
    ],
    [
      190.21414184570312,
      149.36541748046875
    ],
    [
      190.21414184570312,
      169.16656494140625
    ],
    [
      306.25543212890625,
      166.18838500976562
    ],
    [
      306.25543212890625,
      183.92808532714844
    ],
    [
      251.65289306640625,
      190.71658325195312
    ],
    [
      104.53517150878906,
      219.31192016601562
    ],
    [
      121.2041244506836,
      337.6188049316406
    ],
    [
      363.7645263671875,
      219.31192016601562
    ],
    [
      320.013916015625,
      337.6188049316406
    ],
    [
      0.0,
      0.0
    ],
    [
      511.0,
      0.0
    ],
    [
      0.0,
      511.0
    ],
    [
      511.0,
      511.0
    ],
    [
      256.0,
      0.0
    ],
    [
      256.0,
      511.0
    ],
    [
      0.0,
      256.0
    ],
    [
      511.0,
      256.0
    ]
  ],
  "tps_regularization": 0.0001
}
