{
  "geometry_info": {
    "action_names": [
      "eye_spread",
      "eye_compress",
      "eye_squint",
      "eye_raise_left",
      "eye_raise_right",
      "nose_bridge_shift_x",
      "asymmetry_twist"
    ],
    "action_strength": 0.72,
    "action_values": {
      "asymmetry_twist": -0.5624429522409912,
      "eye_compress": 0.15726772408525574,
      "eye_raise_left": 0.11588445113954324,
      "eye_raise_right": -0.577511414403147,
      "eye_spread": 0.4155310088781515,
      "eye_squint": 0.41199862451429764,
      "nose_bridge_shift_x": -0.5004341717618284
    },
    "active_actions": {
      "asymmetry_twist": -0.5624429522409912,
      "eye_compress": 0.15726772408525574,
      "eye_raise_left": 0.11588445113954324,
      "eye_raise_right": -0.577511414403147,
      "eye_spread": 0.4155310088781515,
      "eye_squint": 0.41199862451429764,
      "nose_bridge_shift_x": -0.5004341717618284
    },
    "active_anchor_count": 13,
    "control_point_count": 21,
    "geometry_method": "landmark_piecewise_affine",
    "max_disp_px_budget": 8.0,
    "scale_factor": 0.954869376762457,
    "source_control_points": [
      [
        212.48001098632812,
        217.60000610351562
      ],
      [
        184.32000732421875,
        217.60000610351562
      ],
      [
        299.5199890136719,
        217.60000610351562
      ],
      [
        327.67999267578125,
        217.60000610351562
      ],
      [
        212.48001098632812,
        199.67999267578125
      ],
      [
        212.48001098632812,
        235.52000427246094
      ],
      [
        299.5199890136719,
        199.67999267578125
      ],
      [
        299.5199890136719,
        235.52000427246094
      ],
      [
        256.0,
        263.67999267578125
      ],
      [
        112.63999938964844,
        248.3199920654297
      ],
      [
        174.0800018310547,
        394.239990234375
      ],
      [
        399.3599853515625,
        248.3199920654297
      ],
      [
        337.9200134277344,
        394.239990234375
      ],
      [
        0.0,
        0.0
      ],
      [
        511.0,
        0.0
      ],
      [
        0.0,
        511.0
      ],
      [
        511.0,
        511.0
      ],
      [
        256.0,
        0.0
      ],
      [
        256.0,
        511.0
      ],
      [
        0.0,
        256.0
      ],
      [
        511.0,
        256.0
      ]
    ],
    "target_control_points": [
      [
        210.99241638183594,
        216.93251037597656
      ],
      [
        182.83241271972656,
        217.60000610351562
      ],
      [
        301.0075988769531,
        220.9264678955078
      ],
      [
        329.1676025390625,
        217.60000610351562
      ],
      [
        212.48001098632812,
        201.38560485839844
      ],
      [
        212.48001098632812,
        232.81314086914062
      ],
      [
        299.5199890136719,
        205.37957763671875
      ],
      [
        299.5199890136719,
        234.81011962890625
      ],
      [
        253.11749267578125,
        263.67999267578125
      ],
      [
        112.63999938964844,
        251.55966186523438
      ],
      [
        174.0800018310547,
        395.8598327636719
      ],
      [
        399.3599853515625,
        245.080322265625
      ],
      [
        337.9200134277344,
        392.6201477050781
      ],
      [
        0.0,
        0.0
      ],
      [
        511.0,
        0.0
      ],
      [
        0.0,
        511.0
      ],
      [
        511.0,
        511.0
      ],
      [
        256.0,
        0.0
      ],
      [
        256.0,
        511.0
      ],
      [
        0.0,
        256.0
      ],
      [
        511.0,
        256.0
      ]
    ],
    "tps_regularization": 0.0001
  },
  "names": [
    "scale_logit",
    "action_eye_spread",
    "action_eye_compress",
    "action_eye_squint",
    "action_eye_raise_left",
    "action_eye_raise_right",
    "action_nose_bridge_shift_x",
    "action_asymmetry_twist"
  ],
  "values": [
    1.408491849899292,
    0.4662575423717499,
    0.1662147343158722,
    0.46170300245285034,
    0.12196272611618042,
    -0.700691819190979,
    -0.581957221031189,
    -0.6761733889579773
  ]
}
