{
  "clean_clip_positive_margin": 0.035206615924835205,
  "clean_semantic_success_score": 0.035206615924835205,
  "clip_available": true,
  "clip_semantic_drop": 0.0034035295248031616,
  "clip_warning": null,
  "crop_clip_available": false,
  "crop_clip_warning": null,
  "decision_label": "metric_only_candidate",
  "decision_reasons": [
    "semantic_drop_small:0.0034",
    "semantic_drop_small:0.0034"
  ],
  "edit_failure_score": 0.0034035295248031616,
  "final_attack_score": 0.13333814329356375,
  "full_image_semantic_drop": 0.0034035295248031616,
  "geometry_excess_penalty": 0.0,
  "geometry_excess_penalty_weight": 1.0,
  "identity_or_face_health_available": false,
  "input_damage_penalty": 0.0,
  "input_damage_penalty_weight": 3.0,
  "input_l2": 0.009603106576825733,
  "input_max_abs": 0.4862745404243469,
  "input_mean_abs": 0.0017484229756519198,
  "input_preservation_score": 0.8982912302017212,
  "input_psnr": 40.35176502478498,
  "input_ssim": 0.9898291230201721,
  "max_disp_px_budget": 6.0,
  "output_disruption_score": 0.11972402519435112,
  "output_disruption_weight": 1.0,
  "output_l2": 0.018528697357700328,
  "output_max_abs": 0.4392157196998596,
  "output_mean_abs": 0.00838769506663084,
  "output_psnr": 34.64310224529905,
  "output_ssim": 0.9543907642364502,
  "perturbed_clip_positive_margin": 0.03180308640003204,
  "perturbed_semantic_success_score": 0.03180308640003204,
  "phase2_final_score": 0.13333814329356375,
  "phase2_output_disruption": 0.11972402519435112,
  "phase2_score_formula": "4.0*max(0,semantic_drop)+1.0*output_disruption-3.0*input_damage_penalty-1.0*geometry_excess_penalty",
  "semantic_drop": 0.0034035295248031616,
  "semantic_drop_weight": 4.0,
  "target_input_ssim": 0.9
}
