{
  "clean_clip_positive_margin": 0.045413434505462646,
  "clean_semantic_success_score": 0.045413434505462646,
  "clip_available": true,
  "clip_semantic_drop": 0.0003578662872314453,
  "clip_warning": null,
  "crop_clip_available": false,
  "crop_clip_warning": null,
  "decision_label": "metric_only_candidate",
  "decision_reasons": [
    "semantic_drop_small:0.0004",
    "semantic_drop_small:0.0004"
  ],
  "edit_failure_score": 0.0003578662872314453,
  "final_attack_score": 0.09756015126361876,
  "full_image_semantic_drop": 0.0003578662872314453,
  "geometry_excess_penalty": 0.0,
  "geometry_excess_penalty_weight": 1.0,
  "identity_or_face_health_available": false,
  "input_damage_penalty": 0.0,
  "input_damage_penalty_weight": 3.0,
  "input_l2": 0.01595395604270561,
  "input_max_abs": 0.458823561668396,
  "input_mean_abs": 0.0030202383641153574,
  "input_preservation_score": 0.594695369402568,
  "input_psnr": 35.94263217754572,
  "input_ssim": 0.975681722164154,
  "max_disp_px_budget": 4.0,
  "output_disruption_score": 0.09612868611469298,
  "output_disruption_weight": 1.0,
  "output_l2": 0.01813725725922592,
  "output_max_abs": 0.7921568751335144,
  "output_mean_abs": 0.00405792985111475,
  "output_psnr": 34.828567738289294,
  "output_ssim": 0.9764203429222107,
  "perturbed_clip_positive_margin": 0.0450555682182312,
  "perturbed_semantic_success_score": 0.0450555682182312,
  "phase2_final_score": 0.09756015126361876,
  "phase2_output_disruption": 0.09612868611469298,
  "phase2_score_formula": "4.0*max(0,semantic_drop)+1.0*output_disruption-3.0*input_damage_penalty-1.0*geometry_excess_penalty",
  "semantic_drop": 0.0003578662872314453,
  "semantic_drop_weight": 4.0,
  "target_input_ssim": 0.94
}
