{
  "clean_clip_positive_margin": 0.04853600263595581,
  "clean_semantic_success_score": 0.04853600263595581,
  "clip_available": true,
  "clip_semantic_drop": -0.0012167096138000488,
  "clip_warning": null,
  "crop_clip_available": false,
  "crop_clip_warning": null,
  "decision_label": "metric_only_candidate",
  "decision_reasons": [
    "semantic_drop_nonpositive:-0.0012",
    "semantic_drop_nonpositive:-0.0012"
  ],
  "edit_failure_score": 0.0,
  "final_attack_score": 0.11420678397850198,
  "full_image_semantic_drop": -0.0012167096138000488,
  "geometry_excess_penalty": 0.0,
  "geometry_excess_penalty_weight": 1.0,
  "identity_or_face_health_available": false,
  "input_damage_penalty": 0.0,
  "input_damage_penalty_weight": 3.0,
  "input_l2": 0.01566791786933594,
  "input_max_abs": 0.5215686559677124,
  "input_mean_abs": 0.0032197190448641777,
  "input_preservation_score": 0.6178547541300459,
  "input_psnr": 36.09977427348635,
  "input_ssim": 0.9770712852478027,
  "max_disp_px_budget": 4.0,
  "output_disruption_score": 0.11420678397850198,
  "output_disruption_weight": 1.0,
  "output_l2": 0.02160052781511347,
  "output_max_abs": 0.8549019694328308,
  "output_mean_abs": 0.00538281537592411,
  "output_psnr": 33.31071273217526,
  "output_ssim": 0.9721953272819519,
  "perturbed_clip_positive_margin": 0.04975271224975586,
  "perturbed_semantic_success_score": 0.04975271224975586,
  "phase2_final_score": 0.11420678397850198,
  "phase2_output_disruption": 0.11420678397850198,
  "phase2_score_formula": "4.0*max(0,semantic_drop)+1.0*output_disruption-3.0*input_damage_penalty-1.0*geometry_excess_penalty",
  "semantic_drop": -0.0012167096138000488,
  "semantic_drop_weight": 4.0,
  "target_input_ssim": 0.94
}
