{
  "clean_clip_positive_margin": 0.035206615924835205,
  "clean_semantic_success_score": 0.035206615924835205,
  "clip_available": true,
  "clip_semantic_drop": 9.417533874511719e-06,
  "clip_warning": null,
  "crop_clip_available": false,
  "crop_clip_warning": null,
  "decision_label": "metric_only_candidate",
  "decision_reasons": [
    "semantic_drop_small:0.0000",
    "semantic_drop_small:0.0000"
  ],
  "edit_failure_score": 9.417533874511719e-06,
  "final_attack_score": 0.18337578498255885,
  "full_image_semantic_drop": 9.417533874511719e-06,
  "geometry_excess_penalty": 0.0,
  "geometry_excess_penalty_weight": 1.0,
  "identity_or_face_health_available": false,
  "input_damage_penalty": 0.0,
  "input_damage_penalty_weight": 3.0,
  "input_l2": 0.014592540905303507,
  "input_max_abs": 0.6352941393852234,
  "input_mean_abs": 0.0022982179652899504,
  "input_preservation_score": 0.8525238037109375,
  "input_psnr": 36.71738161233797,
  "input_ssim": 0.9852523803710938,
  "max_disp_px_budget": 6.0,
  "output_disruption_score": 0.1833381148470608,
  "output_disruption_weight": 1.0,
  "output_l2": 0.030335473326175606,
  "output_max_abs": 0.7215686440467834,
  "output_mean_abs": 0.011119416914880276,
  "output_psnr": 30.360984486894132,
  "output_ssim": 0.9380037784576416,
  "perturbed_clip_positive_margin": 0.03519719839096069,
  "perturbed_semantic_success_score": 0.03519719839096069,
  "phase2_final_score": 0.18337578498255885,
  "phase2_output_disruption": 0.1833381148470608,
  "phase2_score_formula": "4.0*max(0,semantic_drop)+1.0*output_disruption-3.0*input_damage_penalty-1.0*geometry_excess_penalty",
  "semantic_drop": 9.417533874511719e-06,
  "semantic_drop_weight": 4.0,
  "target_input_ssim": 0.9
}
