{
  "clean_clip_positive_margin": 0.045523494482040405,
  "clean_semantic_success_score": 0.045523494482040405,
  "clip_available": true,
  "clip_semantic_drop": 0.0013450682163238525,
  "clip_warning": null,
  "crop_clip_available": false,
  "crop_clip_warning": null,
  "decision_label": "metric_only_candidate",
  "decision_reasons": [
    "semantic_drop_small:0.0013",
    "semantic_drop_small:0.0013",
    "semantic_drop_small:0.0013"
  ],
  "edit_failure_score": 0.0013450682163238525,
  "final_attack_score": 0.25044450503474636,
  "full_image_semantic_drop": 0.0013450682163238525,
  "geometry_excess_penalty": 0.0,
  "geometry_excess_penalty_weight": 0.75,
  "identity_or_face_health_available": false,
  "input_damage_penalty": 0.0,
  "input_damage_penalty_weight": 3.0,
  "input_l2": 0.06457121824193517,
  "input_max_abs": 0.8274509906768799,
  "input_mean_abs": 0.02280750870704651,
  "input_preservation_score": 0.268441850488836,
  "input_psnr": 23.799220396783596,
  "input_ssim": 0.839057207107544,
  "max_disp_px_budget": 14.0,
  "output_disruption_score": 0.4793679186083111,
  "output_disruption_weight": 0.5,
  "output_l2": 0.0797856765085765,
  "output_max_abs": 0.9686274528503418,
  "output_mean_abs": 0.026461875066161156,
  "output_psnr": 21.961501363870113,
  "output_ssim": 0.8397747874259949,
  "perturbed_clip_positive_margin": 0.04417842626571655,
  "perturbed_semantic_success_score": 0.04417842626571655,
  "phase2_final_score": 0.25044450503474636,
  "phase2_output_disruption": 0.4793679186083111,
  "phase2_score_formula": "8.0*max(0,semantic_drop)+0.5*output_disruption-3.0*input_damage_penalty-0.75*geometry_excess_penalty",
  "phase4_budget_name": "existence_probe",
  "phase4_final_score": 0.25044450503474636,
  "phase4_score_formula": "8.0*max(0,semantic_drop)+0.5*output_disruption-3.0*input_damage_penalty-0.75*geometry_excess_penalty",
  "semantic_drop": 0.0013450682163238525,
  "semantic_drop_weight": 8.0,
  "target_input_ssim": 0.78
}
