{
  "action_names": [
    "face_side_push_left",
    "face_side_push_right",
    "head_top_raise",
    "head_top_lower",
    "jaw_expand",
    "jaw_compress",
    "asymmetry_twist"
  ],
  "action_strength": 0.72,
  "action_values": {
    "asymmetry_twist": -0.3109967756042307,
    "face_side_push_left": -0.39666741613376216,
    "face_side_push_right": -0.08533537555813578,
    "head_top_lower": 0.35411051391938725,
    "head_top_raise": 0.4830933182349667,
    "jaw_compress": 0.3315710401369483,
    "jaw_expand": 0.3801189963674296
  },
  "active_actions": {
    "asymmetry_twist": -0.3109967756042307,
    "face_side_push_left": -0.39666741613376216,
    "face_side_push_right": -0.08533537555813578,
    "head_top_lower": 0.35411051391938725,
    "head_top_raise": 0.4830933182349667,
    "jaw_compress": 0.3315710401369483,
    "jaw_expand": 0.3801189963674296
  },
  "active_anchor_count": 7,
  "control_point_count": 15,
  "geometry_method": "landmark_semantic_tps",
  "max_disp_px_budget": 14.0,
  "scale_factor": 0.5678105466681849,
  "source_control_points": [
    [
      112.63999938964844,
      248.3199920654297
    ],
    [
      112.63999938964844,
      253.44000244140625
    ],
    [
      399.3599853515625,
      248.3199920654297
    ],
    [
      399.3599853515625,
      253.44000244140625
    ],
    [
      256.0,
      87.04000091552734
    ],
    [
      174.0800018310547,
      394.239990234375
    ],
    [
      337.9200134277344,
      394.239990234375
    ],
    [
      0.0,
      0.0
    ],
    [
      511.0,
      0.0
    ],
    [
      0.0,
      511.0
    ],
    [
      511.0,
      511.0
    ],
    [
      256.0,
      0.0
    ],
    [
      256.0,
      511.0
    ],
    [
      0.0,
      256.0
    ],
    [
      511.0,
      256.0
    ]
  ],
  "target_control_points": [
    [
      116.6384048461914,
      251.454833984375
    ],
    [
      115.63880157470703,
      253.44000244140625
    ],
    [
      398.49981689453125,
      245.18515014648438
    ],
    [
      398.71484375,
      253.44000244140625
    ],
    [
      256.0,
      85.73985290527344
    ],
    [
      173.59063720703125,
      395.8074035644531
    ],
    [
      338.40936279296875,
      392.6725769042969
    ],
    [
      0.0,
      0.0
    ],
    [
      511.0,
      0.0
    ],
    [
      0.0,
      511.0
    ],
    [
      511.0,
      511.0
    ],
    [
      256.0,
      0.0
    ],
    [
      256.0,
      511.0
    ],
    [
      0.0,
      256.0
    ],
    [
      511.0,
      256.0
    ]
  ],
  "tps_regularization": 0.0001
}
