{
  "action_names": [
    "jaw_expand",
    "jaw_compress",
    "chin_raise",
    "chin_lower",
    "mouth_width_expand",
    "lower_face_shift"
  ],
  "action_strength": 0.72,
  "action_values": {
    "chin_lower": 0.427843209616085,
    "chin_raise": -0.685342008827065,
    "jaw_compress": 0.1527084830551043,
    "jaw_expand": 0.4314979304655222,
    "lower_face_shift": 0.2686316791603929,
    "mouth_width_expand": -0.38800955219302136
  },
  "active_actions": {
    "chin_lower": 0.427843209616085,
    "chin_raise": -0.685342008827065,
    "jaw_compress": 0.1527084830551043,
    "jaw_expand": 0.4314979304655222,
    "lower_face_shift": 0.2686316791603929,
    "mouth_width_expand": -0.38800955219302136
  },
  "active_anchor_count": 6,
  "control_point_count": 14,
  "geometry_method": "landmark_piecewise_affine",
  "max_disp_px_budget": 8.0,
  "scale_factor": 0.7530650540833168,
  "source_control_points": [
    [
      174.0800018310547,
      394.239990234375
    ],
    [
      337.9200134277344,
      394.239990234375
    ],
    [
      256.0,
      419.8399963378906
    ],
    [
      256.0,
      376.32000732421875
    ],
    [
      204.8000030517578,
      335.3599853515625
    ],
    [
      307.20001220703125,
      335.3599853515625
    ],
    [
      0.0,
      0.0
    ],
    [
      511.0,
      0.0
    ],
    [
      0.0,
      511.0
    ],
    [
      511.0,
      511.0
    ],
    [
      256.0,
      0.0
    ],
    [
      256.0,
      511.0
    ],
    [
      0.0,
      256.0
    ],
    [
      511.0,
      256.0
    ]
  ],
  "target_control_points": [
    [
      172.47418212890625,
      394.239990234375
    ],
    [
      339.5258483886719,
      394.239990234375
    ],
    [
      257.1604919433594,
      426.251953125
    ],
    [
      257.5473327636719,
      379.5259704589844
    ],
    [
      207.03494262695312,
      335.3599853515625
    ],
    [
      304.965087890625,
      335.3599853515625
    ],
    [
      0.0,
      0.0
    ],
    [
      511.0,
      0.0
    ],
    [
      0.0,
      511.0
    ],
    [
      511.0,
      511.0
    ],
    [
      256.0,
      0.0
    ],
    [
      256.0,
      511.0
    ],
    [
      0.0,
      256.0
    ],
    [
      511.0,
      256.0
    ]
  ],
  "tps_regularization": 0.0001
}
