{
  "geometry_info": {
    "action_names": [
      "eye_spread",
      "eye_compress",
      "eye_squint",
      "eye_raise_left",
      "eye_raise_right",
      "nose_bridge_shift_x",
      "asymmetry_twist"
    ],
    "action_strength": 0.72,
    "action_values": {
      "asymmetry_twist": 0.27977125008075454,
      "eye_compress": -0.7689242851015873,
      "eye_raise_left": -0.670223942887658,
      "eye_raise_right": -0.3156830860119557,
      "eye_spread": 0.8509855789290375,
      "eye_squint": -0.5394750480107172,
      "nose_bridge_shift_x": -0.08826811668391876
    },
    "active_actions": {
      "asymmetry_twist": 0.27977125008075454,
      "eye_compress": -0.7689242851015873,
      "eye_raise_left": -0.670223942887658,
      "eye_raise_right": -0.3156830860119557,
      "eye_spread": 0.8509855789290375,
      "eye_squint": -0.5394750480107172,
      "nose_bridge_shift_x": -0.08826811668391876
    },
    "active_anchor_count": 13,
    "control_point_count": 21,
    "geometry_method": "landmark_piecewise_affine",
    "max_disp_px_budget": 14.0,
    "scale_factor": 0.9102468826721768,
    "source_control_points": [
      [
        212.48001098632812,
        217.60000610351562
      ],
      [
        184.32000732421875,
        217.60000610351562
      ],
      [
        299.5199890136719,
        217.60000610351562
      ],
      [
        327.67999267578125,
        217.60000610351562
      ],
      [
        212.48001098632812,
        199.67999267578125
      ],
      [
        212.48001098632812,
        235.52000427246094
      ],
      [
        299.5199890136719,
        199.67999267578125
      ],
      [
        299.5199890136719,
        235.52000427246094
      ],
      [
        256.0,
        263.67999267578125
      ],
      [
        112.63999938964844,
        248.3199920654297
      ],
      [
        174.0800018310547,
        394.239990234375
      ],
      [
        399.3599853515625,
        248.3199920654297
      ],
      [
        337.9200134277344,
        394.239990234375
      ],
      [
        0.0,
        0.0
      ],
      [
        511.0,
        0.0
      ],
      [
        0.0,
        511.0
      ],
      [
        511.0,
        511.0
      ],
      [
        256.0,
        0.0
      ],
      [
        256.0,
        511.0
      ],
      [
        0.0,
        256.0
      ],
      [
        511.0,
        256.0
      ]
    ],
    "target_control_points": [
      [
        196.1513214111328,
        224.35586547851562
      ],
      [
        167.99131774902344,
        217.60000610351562
      ],
      [
        315.84869384765625,
        220.78208923339844
      ],
      [
        344.0086975097656,
        217.60000610351562
      ],
      [
        212.48001098632812,
        200.99794006347656
      ],
      [
        212.48001098632812,
        244.33584594726562
      ],
      [
        299.5199890136719,
        197.42416381835938
      ],
      [
        299.5199890136719,
        242.5489501953125
      ],
      [
        255.11026000976562,
        263.67999267578125
      ],
      [
        112.63999938964844,
        245.49989318847656
      ],
      [
        174.0800018310547,
        392.8299560546875
      ],
      [
        399.3599853515625,
        251.1400909423828
      ],
      [
        337.9200134277344,
        395.6500244140625
      ],
      [
        0.0,
        0.0
      ],
      [
        511.0,
        0.0
      ],
      [
        0.0,
        511.0
      ],
      [
        511.0,
        511.0
      ],
      [
        256.0,
        0.0
      ],
      [
        256.0,
        511.0
      ],
      [
        0.0,
        256.0
      ],
      [
        511.0,
        256.0
      ]
    ],
    "tps_regularization": 0.0001
  },
  "names": [
    "scale_logit",
    "action_eye_spread",
    "action_eye_compress",
    "action_eye_squint",
    "action_eye_raise_left",
    "action_eye_raise_right",
    "action_nose_bridge_shift_x",
    "action_asymmetry_twist"
  ],
  "values": [
    1.034274935722351,
    1.6959062814712524,
    -1.2375051975250244,
    -0.6817700862884521,
    -0.9423717856407166,
    -0.361813485622406,
    -0.09727730602025986,
    0.31762465834617615
  ]
}
